nr/__init__.py
nr/utils/__init__.py
nr/utils/re/__init__.py
nr/utils/re/py.typed
nr.utils.re-0.3.1.dist-info/LICENSE.txt
nr.utils.re-0.3.1.dist-info/METADATA
nr.utils.re-0.3.1.dist-info/WHEEL
nr.utils.re-0.3.1.dist-info/top_level.txt
nr.utils.re-0.3.1.dist-info/RECORD
