Metadata-Version: 2.1
Name: nr.utils.re
Version: 0.3.1
Summary: This module provides some utility functions for applying regular expressions.
Home-page: https://git.niklasrosenstein.com/NiklasRosenstein/nr
Author: Niklas Rosenstein
Author-email: rosensteinniklas@gmail.com
License: MIT
Platform: UNKNOWN
Requires-Python: >=3.6.0,<4.0.0
